{"changes": {"content": {"new": "Test **text _BoldItalics_** _italics_\r\n\r\nunderline ~~strikethrough~~\r\n\r\n`some_line_code()`\r\n\r\nxn x2\r\n\r\n* dot point 1\r\n* dot point 2\r\n\r\nasdf\r\n\r\n## Heading 2\r\n\r\ndivider:\r\n\r\n---\r\n\r\nnumbered list:\r\n\r\n1. thing in a numbered list\r\n2. another thing\r\n\r\n@{557058:2f99420c-1dbd-4837-952c-82c421b8fbdd} @{557058:52a111e4-40da-4441-9143-417f95f2db97}\r\n\r\n:grinning:\r\n\r\n| **col 1** | **col 2** | **col 3** |\r\n| --- | --- | --- |\r\n| item 1 | item 3 | item 5 |\r\n| item 2 | item 4 | item 6 |\r\n\r\n> quoted text\r\n\r\n\u200c\r\n\r\n```python\r\nimport module\r\nmodule.function()\r\nfor i in range(10):\r\n  print(i)\r\n```\r\n\r\nLink to [google](https://google.com)\r\n\r\nImage:\r\n\r\n![](https://bitbucket.org/repo/Rg5nLg/images/2813476062-HZD%20wallpaper.jpg)\r\n\u200c", "old": "Test **text _BoldItalics_** _italics_\r\n\r\nunderline ~~strikethrough~~\r\n\r\n`some_line_code()`\r\n\r\nxn x2\r\n\r\n* dot point 1\r\n* dot point 2\r\n\r\nasdf\r\n\r\n## Heading 2\r\n\r\ndivider:\r\n\r\n---\r\n\r\nnumbered list:\r\n\r\n1. thing in a numbered list\r\n2. another thing\r\n\r\n@{557058:2f99420c-1dbd-4837-952c-82c421b8fbdd} @{557058:52a111e4-40da-4441-9143-417f95f2db97} \r\n\r\n:grinning: \r\n\r\n| **col 1** | **col 2** | **col 3** |\r\n| --- | --- | --- |\r\n| item 1 | item 3 | item 5 |\r\n| item 2 | item 4 | item 6 |\r\n\r\n> quoted text\r\n\r\n\u200c\r\n\r\n```python\r\nimport module\r\nmodule.function()\r\nfor i in range(10):\r\n  print(i)\r\n```\r\n\r\nLink to [google](https://google.com)\r\n\r\nImage:\r\n\r\n![](https://bitbucket.org/repo/Rg5nLg/images/2813476062-HZD%20wallpaper.jpg)\r\n\u200c"}}, "links": {"self": {"href": "data/repositories/philipstarkey/qtutils/issues/7/changes/54272990.json"}, "html": {"href": "#!/philipstarkey/qtutils/issues/7#comment-54272990"}}, "issue": {"links": {"self": {"href": "data/repositories/philipstarkey/qtutils/issues/7.json"}}, "type": "issue", "id": 7, "repository": {"links": {"self": {"href": "data/repositories/philipstarkey/qtutils.json"}, "html": {"href": "#!/philipstarkey/qtutils"}, "avatar": {"href": "data/bytebucket.org/ravatar/{eb85b0e6-11dc-449a-96ec-21935a03d721}ts=python"}}, "type": "repository", "name": "qtutils", "full_name": "philipstarkey/qtutils", "uuid": "{eb85b0e6-11dc-449a-96ec-21935a03d721}"}, "title": "Test issue for exporter to GitHub"}, "created_on": "2019-10-09T11:47:34.307036+00:00", "user": {"display_name": "Philip Starkey", "uuid": "{0147401a-13ed-4e39-a0d0-63108c18738b}", "links": {"self": {"href": "https://api.bitbucket.org/2.0/users/%7B0147401a-13ed-4e39-a0d0-63108c18738b%7D"}, "html": {"href": "https://bitbucket.org/%7B0147401a-13ed-4e39-a0d0-63108c18738b%7D/"}, "avatar": {"href": "data/secure.gravatar.com/avatar/fa0698c306b3470c00717c146b5296e9d=httpsavatar-management--avatars.us-west-2.prod.public.atl-paas.netinitialsPS-0.png"}}, "nickname": "philipstarkey", "type": "user", "account_id": "557058:2f99420c-1dbd-4837-952c-82c421b8fbdd"}, "message": {"raw": null, "markup": "markdown", "html": "", "type": "rendered"}, "type": "issue_change", "id": 54272990}